README.rst
setup.cfg
setup.py
NoseXUnitLite.egg-info/PKG-INFO
NoseXUnitLite.egg-info/SOURCES.txt
NoseXUnitLite.egg-info/dependency_links.txt
NoseXUnitLite.egg-info/entry_points.txt
NoseXUnitLite.egg-info/requires.txt
NoseXUnitLite.egg-info/top_level.txt
NoseXUnitLite.egg-info/zip-safe
nosexunitlite/__init__.py
nosexunitlite/const.py
nosexunitlite/core.py
nosexunitlite/cyclo.py
nosexunitlite/excepts.py
nosexunitlite/plugin.py
nosexunitlite/tools.py